openui/__init__.py
openui-0.0.1.dist-info/LICENSE
openui-0.0.1.dist-info/METADATA
openui-0.0.1.dist-info/WHEEL
openui-0.0.1.dist-info/top_level.txt
openui-0.0.1.dist-info/RECORD
